DLTrainer/__init__.py
DLTrainer/pytorch/__init__.py
DLTrainer/pytorch/trainer.py
DLTrainer/pytorch/trainer_utils.py
DLTrainer-0.1.2.dist-info/LICENSE
DLTrainer-0.1.2.dist-info/METADATA
DLTrainer-0.1.2.dist-info/WHEEL
DLTrainer-0.1.2.dist-info/top_level.txt
DLTrainer-0.1.2.dist-info/RECORD
