Metadata-Version: 2.1
Name: DLTrainer
Version: 0.1.2
Summary: DLTrainer is an easy to use framework for quickly setting up deep learning experiments. This includes CPU, single GPU and distributed GPU experiments. Currently, this package only supports PyTorch. This packages is primarily designed for running experiments from the command line, so that workloads can be easily ran in the cloud.
Home-page: https://github.com/nickvasko/DLTrainer
Author: Nick Vasko
Author-email: nicholas.d.vasko@gmail.com
License: UNKNOWN
Project-URL: Bug Tracker, https://github.com/nickvasko/DLTrainer/issues
Platform: UNKNOWN
Classifier: Programming Language :: Python :: 3
Classifier: License :: OSI Approved :: MIT License
Classifier: Operating System :: OS Independent
Requires-Python: >=3.6
License-File: LICENSE
